{
  "name": "pong",
  "repo": "whirlibulf/pong",
  "description": "",
  "version": "0.0.1",
  "keywords": [],
  "dependencies": {
    "whirlibulf/engine": "*",
    "whirlibulf/2d-canvas-system": "*",
    "whirlibulf/stats.js-system": "*",
    "whirlibulf/position-component": "*",
    "whirlibulf/size-component": "*",
    "whirlibulf/renderable-component": "*",
    "whirlibulf/color-component": "*",
    "whirlibulf/kinematics-system": "*",
    "whirlibulf/velocity-component": "*",
    "whirlibulf/keyboard-system": "*",
    "whirlibulf/script-component": "*",
    "whirlibulf/script-system": "*"
  },
  "development": {},
  "license": "MIT",
  "main": "index.js",
  "scripts": [
    "index.js",
    "entities/background.js",
    "entities/player.js",
    "entities/computer.js",
    "entities/ball.js",
    "scripts/controls.js",
    "scripts/ai.js",
    "scripts/wallCollision.js",
    "scripts/paddleCollision.js"
  ]
}
